qiskit_symb/__init__.py
qiskit_symb/circuit/__init__.py
qiskit_symb/circuit/gate.py
qiskit_symb/circuit/parametricgate.py
qiskit_symb/circuit/random.py
qiskit_symb/circuit/standardgate.py
qiskit_symb/circuit/library/__init__.py
qiskit_symb/circuit/library/parametric_gates/__init__.py
qiskit_symb/circuit/library/parametric_gates/p.py
qiskit_symb/circuit/library/parametric_gates/r.py
qiskit_symb/circuit/library/parametric_gates/rx.py
qiskit_symb/circuit/library/parametric_gates/rxx.py
qiskit_symb/circuit/library/parametric_gates/ry.py
qiskit_symb/circuit/library/parametric_gates/ryy.py
qiskit_symb/circuit/library/parametric_gates/rz.py
qiskit_symb/circuit/library/parametric_gates/rzz.py
qiskit_symb/circuit/library/parametric_gates/u.py
qiskit_symb/circuit/library/standard_gates/__init__.py
qiskit_symb/circuit/library/standard_gates/dcx.py
qiskit_symb/circuit/library/standard_gates/ecr.py
qiskit_symb/circuit/library/standard_gates/h.py
qiskit_symb/circuit/library/standard_gates/i.py
qiskit_symb/circuit/library/standard_gates/iswap.py
qiskit_symb/circuit/library/standard_gates/s.py
qiskit_symb/circuit/library/standard_gates/swap.py
qiskit_symb/circuit/library/standard_gates/sx.py
qiskit_symb/circuit/library/standard_gates/t.py
qiskit_symb/circuit/library/standard_gates/x.py
qiskit_symb/circuit/library/standard_gates/y.py
qiskit_symb/circuit/library/standard_gates/z.py
qiskit_symb/quantum_info/__init__.py
qiskit_symb/quantum_info/statevector.py
qiskit_symb-0.5.0.dist-info/licenses/LICENSE
qiskit_symb-0.5.0.dist-info/METADATA
qiskit_symb-0.5.0.dist-info/WHEEL
qiskit_symb-0.5.0.dist-info/top_level.txt
qiskit_symb-0.5.0.dist-info/RECORD
