Metadata-Version: 2.4
Name: qiskit-symb
Version: 0.5.0
Summary: Symbolic evaluation of parameterized quantum circuits in Qiskit
Author-email: Simone Gasperini <simone.gasperini4@unibo.it>
License: Apache-2.0
Keywords: quantum-computing,symbolic-computation,qiskit,sympy
Classifier: Programming Language :: Python :: 3
Classifier: License :: OSI Approved :: Apache Software License
Classifier: Operating System :: POSIX :: Linux
Classifier: Operating System :: MacOS
Classifier: Operating System :: Microsoft :: Windows
Requires-Python: >=3.9
License-File: LICENSE
Requires-Dist: qiskit<2.0
Requires-Dist: opt_einsum
Dynamic: license-file
